LICENSE
README.md
setup.py
mlda/__init__.py
mlda/obs.py
mlda/prior.py
mlda/psm.py
mlda/utils.py
mlda.egg-info/PKG-INFO
mlda.egg-info/SOURCES.txt
mlda.egg-info/dependency_links.txt
mlda.egg-info/not-zip-safe
mlda.egg-info/requires.txt
mlda.egg-info/top_level.txt
mlda/cesm/__init__.py
mlda/cesm/cesm.py
mlda/enkf/__init__.py
mlda/enkf/solver.py
mlda/nn/__init__.py
mlda/nn/data.py
mlda/nn/model.py
mlda/nn/predictor.py
mlda/nn/trainer.py