Metadata-Version: 2.1
Name: mlda
Version: 2025.5.18
Summary: mlda: A Python package for Machine Learning-base Data Assimilation
Home-page: https://github.com/fzhu2e/mlda
Author: Feng Zhu
Author-email: fengzhu@ucar.edu
License: BSD-3
Keywords: Machine Learning,Data Assimilation
Classifier: Natural Language :: English
Classifier: Programming Language :: Python :: 3.12
License-File: LICENSE
Requires-Dist: netCDF4
Requires-Dist: xarray
Requires-Dist: dask
Requires-Dist: nc-time-axis
Requires-Dist: colorama
Requires-Dist: tqdm
Requires-Dist: x4c-exp
